proxychecker/__init__.py
proxychecker/proxychecker.py
py_proxy_checker-0.2.2.dist-info/METADATA
py_proxy_checker-0.2.2.dist-info/WHEEL
py_proxy_checker-0.2.2.dist-info/top_level.txt
py_proxy_checker-0.2.2.dist-info/RECORD
