Metadata-Version: 2.1
Name: py-proxy-checker
Version: 0.2.2
Summary: Proxy Checker is a python package that allows you to check the validity of a proxy
Home-page: https://github.com/yassine20011/py-proxy-checker
Author: Yassine Amjad
Author-email: Yassine.amjad001@gmail.com
License: MIT
Keywords: proxy checker
Classifier: Programming Language :: Python :: 3
Classifier: License :: OSI Approved :: MIT License
Classifier: Operating System :: OS Independent
Requires-Python: >=3.6
Requires-Dist: requests
